{
    "play_area": {
        "top": 156,
        "left": 731,
        "width": 452,
        "height": 713
    },
    "combo_area": {
        "top": 337,
        "left": 1460,
        "width": 150,
        "height": 41
    },
    "score_area": {
        "top": 216,
        "left": 1416,
        "width": 222,
        "height": 56
    },
    "accuracy_area": {
        "top": 286,
        "left": 1510,
        "width": 62,
        "height": 38
    },
    "mode": "mania",
    "num_keys": 7,
    "max_steps": 15000,
    "training_params": {
        "policy": "CnnPolicy",
        "total_timesteps": 100000,
        "ppo_params": {
            "n_steps": 512,
            "batch_size": 32,
            "ent_coef": 0.01,
            "learning_rate": 0.00025,
            "clip_range": 0.2,
            "n_epochs": 4
        },
        "callback_params": {
            "checkpoint_save_freq": 10000,
            "eval_freq": 5000,
            "n_eval_episodes": 5
        }
    },
    "timestamp": "2025-09-23 20:50:16"
}
